LICENSE
MANIFEST.in
README.rst
setup.py
django_odesk_auth/__init__.py
django_odesk_auth/backends.py
django_odesk_auth/models.py
django_odesk_auth/tests.py
django_odesk_auth/urls.py
django_odesk_auth/utils.py
django_odesk_auth/views.py
django_odesk_auth.egg-info/PKG-INFO
django_odesk_auth.egg-info/SOURCES.txt
django_odesk_auth.egg-info/dependency_links.txt
django_odesk_auth.egg-info/top_level.txt